codema_dev_tasks/__init__.py
codema_dev_tasks/_compat.py
codema_dev_tasks/contracts.py
codema_dev_tasks/hooks.py
codema_dev_tasks/requests.py
codema_dev_tasks-0.2.0.dist-info/LICENSE
codema_dev_tasks-0.2.0.dist-info/WHEEL
codema_dev_tasks-0.2.0.dist-info/METADATA
codema_dev_tasks-0.2.0.dist-info/RECORD
